[
  {
    "file": "src/kernel.cpp",
    "directory": "/home/c/w/uefi-os",
    "arguments": [
      "clang++",
      "-std=c++23",
      "-ffreestanding",
      "-fno-stack-protector",
      "-fno-exceptions",
      "-fno-rtti",
      "-mno-red-zone",
    ],
  },
  {
    "file": "src/gdt.s",
    "directory": "/home/c/w/uefi-os",
    "arguments": [
      "clang",
      "-target",
      "x86_64-unknown-windows-msvc",
    ],
  },
  {
    "file": "src/uefi.cpp",
    "directory": "/home/c/w/uefi-os",
    "arguments": [
      "clang++",
      "-std=c++23",
      "-target",
      "x86_64-unknown-windows-msvc",
      "-ffreestanding",
      "-fno-stack-protector",
      "-mno-red-zone",
      "-I",
      "/usr/include/efi/",
    ],
  }
]
